{
  "title": "Astana, Part 21",
  "slug": "june-2023-astana-part-21",
  "summary": "June 2023, Astana",
  "cardLocation": "Kazakhstan",
  "location": "Astana",
  "timeframe": "June 2023",
  "legacyPath": "/june-2023",
  "sortOrder": 39,
  "cover": {
    "src": "/photo-imports/june-2023/images/044.jpg",
    "width": 1920,
    "height": 1280
  },
  "photos": [
    {
      "src": "/photo-imports/june-2023/images/001.jpg",
      "width": 1707,
      "height": 2560,
      "size": 1403244
    },
    {
      "src": "/photo-imports/june-2023/images/002.jpg",
      "width": 1707,
      "height": 2560,
      "size": 1226962
    },
    {
      "src": "/photo-imports/june-2023/images/003.jpg",
      "width": 1707,
      "height": 2560,
      "size": 1431076
    },
    {
      "src": "/photo-imports/june-2023/images/004.jpg",
      "width": 1707,
      "height": 2560,
      "size": 1793962
    },
    {
      "src": "/photo-imports/june-2023/images/005.jpg",
      "width": 1707,
      "height": 2560,
      "size": 1630481
    },
    {
      "src": "/photo-imports/june-2023/images/006.jpg",
      "width": 1706,
      "height": 2560,
      "size": 1370393
    },
    {
      "src": "/photo-imports/june-2023/images/007.jpg",
      "width": 1707,
      "height": 2560,
      "size": 1489727
    },
    {
      "src": "/photo-imports/june-2023/images/008.jpg",
      "width": 1707,
      "height": 2560,
      "size": 1351965
    },
    {
      "src": "/photo-imports/june-2023/images/009.jpg",
      "width": 1707,
      "height": 2560,
      "size": 1468606
    },
    {
      "src": "/photo-imports/june-2023/images/010.jpg",
      "width": 1707,
      "height": 2560,
      "size": 1162886
    },
    {
      "src": "/photo-imports/june-2023/images/011.jpg",
      "width": 1707,
      "height": 2560,
      "size": 1458942
    },
    {
      "src": "/photo-imports/june-2023/images/012.jpg",
      "width": 1707,
      "height": 2560,
      "size": 1198405
    },
    {
      "src": "/photo-imports/june-2023/images/013.jpg",
      "width": 1707,
      "height": 2560,
      "size": 1600589
    },
    {
      "src": "/photo-imports/june-2023/images/014.jpg",
      "width": 1707,
      "height": 2560,
      "size": 1340226
    },
    {
      "src": "/photo-imports/june-2023/images/015.jpg",
      "width": 1707,
      "height": 2560,
      "size": 1239865
    },
    {
      "src": "/photo-imports/june-2023/images/016.jpg",
      "width": 1707,
      "height": 2560,
      "size": 1584585
    },
    {
      "src": "/photo-imports/june-2023/images/017.jpg",
      "width": 1920,
      "height": 1280,
      "size": 1175889
    },
    {
      "src": "/photo-imports/june-2023/images/018.jpg",
      "width": 1706,
      "height": 2560,
      "size": 1184500
    },
    {
      "src": "/photo-imports/june-2023/images/019.jpg",
      "width": 1707,
      "height": 2560,
      "size": 1216959
    },
    {
      "src": "/photo-imports/june-2023/images/020.jpg",
      "width": 1707,
      "height": 2560,
      "size": 1438418
    },
    {
      "src": "/photo-imports/june-2023/images/021.jpg",
      "width": 1707,
      "height": 2560,
      "size": 1822429
    },
    {
      "src": "/photo-imports/june-2023/images/022.jpg",
      "width": 1707,
      "height": 2560,
      "size": 1288466
    },
    {
      "src": "/photo-imports/june-2023/images/023.jpg",
      "width": 1707,
      "height": 2560,
      "size": 1346776
    },
    {
      "src": "/photo-imports/june-2023/images/024.jpg",
      "width": 1707,
      "height": 2560,
      "size": 1258381
    },
    {
      "src": "/photo-imports/june-2023/images/025.jpg",
      "width": 1707,
      "height": 2560,
      "size": 1156425
    },
    {
      "src": "/photo-imports/june-2023/images/026.jpg",
      "width": 1707,
      "height": 2560,
      "size": 1265850
    },
    {
      "src": "/photo-imports/june-2023/images/027.jpg",
      "width": 1706,
      "height": 2560,
      "size": 1114379
    },
    {
      "src": "/photo-imports/june-2023/images/028.jpg",
      "width": 1706,
      "height": 2560,
      "size": 1287048
    },
    {
      "src": "/photo-imports/june-2023/images/029.jpg",
      "width": 1920,
      "height": 1280,
      "size": 1180009
    },
    {
      "src": "/photo-imports/june-2023/images/030.jpg",
      "width": 1706,
      "height": 2560,
      "size": 970904
    },
    {
      "src": "/photo-imports/june-2023/images/031.jpg",
      "width": 1707,
      "height": 2560,
      "size": 1908403
    },
    {
      "src": "/photo-imports/june-2023/images/032.jpg",
      "width": 1706,
      "height": 2560,
      "size": 1570864
    },
    {
      "src": "/photo-imports/june-2023/images/033.jpg",
      "width": 1707,
      "height": 2560,
      "size": 2240511
    },
    {
      "src": "/photo-imports/june-2023/images/034.jpg",
      "width": 1707,
      "height": 2560,
      "size": 1286971
    },
    {
      "src": "/photo-imports/june-2023/images/035.jpg",
      "width": 1920,
      "height": 1280,
      "size": 1241065
    },
    {
      "src": "/photo-imports/june-2023/images/036.jpg",
      "width": 1706,
      "height": 2560,
      "size": 1375105
    },
    {
      "src": "/photo-imports/june-2023/images/037.jpg",
      "width": 1707,
      "height": 2560,
      "size": 1382298
    },
    {
      "src": "/photo-imports/june-2023/images/038.jpg",
      "width": 1707,
      "height": 2560,
      "size": 1551962
    },
    {
      "src": "/photo-imports/june-2023/images/039.jpg",
      "width": 1707,
      "height": 2560,
      "size": 2019058
    },
    {
      "src": "/photo-imports/june-2023/images/040.jpg",
      "width": 1920,
      "height": 1280,
      "size": 1328913
    },
    {
      "src": "/photo-imports/june-2023/images/041.jpg",
      "width": 1707,
      "height": 2560,
      "size": 1185232
    },
    {
      "src": "/photo-imports/june-2023/images/042.jpg",
      "width": 1706,
      "height": 2560,
      "size": 1392714
    },
    {
      "src": "/photo-imports/june-2023/images/043.jpg",
      "width": 1707,
      "height": 2560,
      "size": 1919531
    },
    {
      "src": "/photo-imports/june-2023/images/044.jpg",
      "width": 1920,
      "height": 1280,
      "size": 1322009
    },
    {
      "src": "/photo-imports/june-2023/images/045.jpg",
      "width": 1707,
      "height": 2560,
      "size": 1413068
    },
    {
      "src": "/photo-imports/june-2023/images/046.jpg",
      "width": 1707,
      "height": 2560,
      "size": 1529964
    }
  ]
}
